example/__init__.py
example/manage.py
example/settings.py
example/example/__init__.py
example/example/apps/__init__.py
example/example/apps/core/__init__.py
example/example/apps/core/apps.py
example/example/apps/core/urls.py
example/example/apps/core/views.py
example/example/apps/core/migrations/__init__.py
example/example/apps/userplayground/__init__.py
example/example/apps/userplayground/admin.py
example/example/apps/userplayground/apps.py
example/example/apps/userplayground/forms.py
example/example/apps/userplayground/models.py
example/example/apps/userplayground/tests.py
example/example/apps/userplayground/urls.py
example/example/apps/userplayground/views.py
example/example/apps/userplayground/migrations/__init__.py
userdefinedtables/__init__.py
userdefinedtables/admin.py
userdefinedtables/apps.py
userdefinedtables/model_mixins.py
userdefinedtables/models.py
userdefinedtables/settings.py
userdefinedtables/views.py
userdefinedtables/migrations/0001_initial.py
userdefinedtables/migrations/__init__.py
userdefinedtables/tests/__init__.py
userdefinedtables/tests/test_column.py
userdefinedtables/tests/test_currencycolumn.py
userdefinedtables/tests/test_currencyentry.py
userdefinedtables/tests/test_datetimecolumn.py
userdefinedtables/tests/test_datetimecolumnentry.py
userdefinedtables/tests/test_entry.py
userdefinedtables/tests/test_numbercolumn.py
userdefinedtables/tests/test_numberentry.py
userdefinedtables/tests/test_orderable_mixin.py
userdefinedtables/tests/test_row.py
userdefinedtables/tests/test_singlelineoftextcolumn.py
userdefinedtables/tests/test_singlelineoftextcolumnentry.py
django_userdefinedtables-0.0.14.dist-info/LICENSE
django_userdefinedtables-0.0.14.dist-info/METADATA
django_userdefinedtables-0.0.14.dist-info/WHEEL
django_userdefinedtables-0.0.14.dist-info/top_level.txt
django_userdefinedtables-0.0.14.dist-info/RECORD
