Metadata-Version: 2.1
Name: django-userdefinedtables
Version: 0.0.14
Summary: Generic EAV-style table creation in the user's hands
Home-page: https://github.com/peterelmwood/django_userdefinedtables
Author: Peter Wood
Author-email: peterelmwood@gmail.com
Maintainer: Peter Wood
License: MIT
Classifier: Development Status :: 3 - Alpha
Classifier: Environment :: Web Environment
Classifier: Intended Audience :: Developers
Classifier: License :: OSI Approved :: MIT License
Classifier: Operating System :: OS Independent
Classifier: Programming Language :: Python
Classifier: Programming Language :: Python :: 3
Classifier: Programming Language :: Python :: 3.6
Classifier: Programming Language :: Python :: 3.7
Classifier: Programming Language :: Python :: 3.8
Classifier: Programming Language :: Python :: 3.9
Classifier: Programming Language :: Python :: 3.10
Classifier: Framework :: Django
Classifier: Framework :: Django :: 2.2
Classifier: Framework :: Django :: 3.1
Classifier: Framework :: Django :: 3.2
Classifier: Framework :: Django :: 4.0
License-File: LICENSE
Requires-Dist: Django (>=2.2)
Requires-Dist: Pillow
Requires-Dist: django-bootstrap-v5
